examplepro_1/__init__.py
examplepro_1-1.0.3.dist-info/LICENSE
examplepro_1-1.0.3.dist-info/METADATA
examplepro_1-1.0.3.dist-info/WHEEL
examplepro_1-1.0.3.dist-info/top_level.txt
examplepro_1-1.0.3.dist-info/RECORD
