Metadata-Version: 2.1
Name: examplepro-1
Version: 1.0.3
Summary: only a test 
Author: Dominik Wuttke
License: Apache License
License-File: LICENSE
